econll/__init__.py
econll/__main__.py
econll/aligner.py
econll/converter.py
econll/decisor.py
econll/indexer.py
econll/parser.py
econll/reader.py
econll/rebaser.py
econll/schemer.py
econll/scorer.py
econll/stats.py
econll/tabler.py
econll/utils.py
econll/xcoder.py
econll-0.3.0.dist-info/LICENSE
econll-0.3.0.dist-info/METADATA
econll-0.3.0.dist-info/WHEEL
econll-0.3.0.dist-info/top_level.txt
econll-0.3.0.dist-info/RECORD
