Metadata-Version: 2.1
Name: econll
Version: 0.3.0
Summary: Extended CoNLL Utilities for Shallow Parsing
Home-page: https://github.com/esrel/econll
Author: Evgeny A. Stepanov
Author-email: stepanov.evgeny.a@gmail.com
Classifier: Development Status :: 3 - Alpha
Classifier: Programming Language :: Python :: 3.10
Classifier: License :: OSI Approved :: GNU Library or Lesser General Public License (LGPL)
Classifier: Topic :: Scientific/Engineering :: Artificial Intelligence
Classifier: Intended Audience :: Science/Research
Requires-Python: >=3.10
License-File: LICENSE
